PROJET_INFO.srcs/sources_1/new/ram.vhd
----------------------------------------------------------------------------------
-- Company: 
-- Engineer: 
-- 
-- Create Date: 18.04.2025
-- Design Name: 
-- Module Name: ram - Behavioral
-- Project Name: 
-- Target Devices: 
-- Tool Versions: 
-- Description: 
-- 
-- Dependencies: 
-- 
-- Revision:
-- Revision 0.01 - File Created
-- Additional Comments:
-- 
----------------------------------------------------------------------------------


library IEEE;
use IEEE.STD_LOGIC_1164.ALL;
use IEEE.numeric_std.ALL;

use work.registers_pkg.all;

entity ram is

    Port ( 
        addr : in std_logic_vector(7 downto 0);
        rw, rst, clk : in std_logic;
        din : in std_logic_vector(7 downto 0);
        dout : out std_logic_vector(7 downto 0)
    );
end ram;

architecture Behavioral of ram is

    signal regs : register_array(0 to 255);

begin

    process (clk)
    begin
        if rising_edge(clk) then
            if (rst = '0') then
                for i in 0 to 255 loop
                    regs(i) <= (others => '0');
                end loop;            
            elsif (rw = '0') then -- write
                regs(to_integer(unsigned(addr))) <= din;
            elsif (rw = '1') then -- read
                dout <= regs(to_integer(unsigned(addr)));
            end if;
        end if;
        
    end process;

end Behavioral;

PROJET_INFO.srcs/sources_1/new/alu.vhd
library IEEE;
use IEEE.STD_LOGIC_1164.ALL;
use IEEE.std_logic_unsigned.ALL; 
use IEEE.numeric_std.ALL;

entity alu is
    Port(
        din_a : in std_logic_vector(7 downto 0);
        din_b : in std_logic_vector(7 downto 0);
        dout : out std_logic_vector(7 downto 0);
        op : in std_logic_vector(3 downto 0);
        
        fcarry : out std_logic;
        foverflow : out std_logic;
        fnegative : out std_logic;
        fzero : out std_logic
    );
end alu;

architecture Behavioral of alu is
    signal tmp : std_logic_vector(7 downto 0) := (others => '0');
begin

    tmp <=  din_a + din_b    when op = "0001" else -- Add
            din_a - din_b   when op = "0011" else -- Sub
            std_logic_vector(resize(unsigned(din_a) * unsigned(din_b), 8)) when op = "0010" else
            std_logic_vector(resize(unsigned(din_a) / unsigned(din_b), 8)) when op = "0100"  else
            std_logic_vector(to_unsigned(boolean'pos(unsigned(din_a) < unsigned(din_b)), 8)) when op = "1001" else
            std_logic_vector(to_unsigned(boolean'pos(unsigned(din_a) > unsigned(din_b)), 8)) when op = "1010" else
            std_logic_vector(to_unsigned(boolean'pos(unsigned(din_a) = unsigned(din_b)), 8)) when op = "1011" else
            --din_a and din_b when op = "000" else -- AND
            --din_a or din_b  when op = "101" else  -- OR
            --din_a xor din_b when op = "110" else -- XOR
            --not din_a       when op = "111" else -- NOT
            X"00";
            
    fcarry <= '1' when (('0' & din_a) + ('0' & din_b)) > "11111111" and op = "0001" else '0';
    foverflow <= '1' when std_logic_vector(unsigned(din_a) * unsigned(din_b)) > "0000000011111111" and op = "0010" else '0';
    fnegative <= '1' when din_a < din_b and op = "0011" else '0';
    fzero <= '1' when tmp = "00000000" else '0';
    
    dout <= tmp;
          
end Behavioral;

PROJET_INFO.srcs/sources_1/new/registers.vhd
----------------------------------------------------------------------------------
-- Company: 
-- Engineer: 
-- 
-- Create Date: 11.04.2025 10:29:56
-- Design Name: 
-- Module Name: registers - Behavioral
-- Project Name: 
-- Target Devices: 
-- Tool Versions: 
-- Description: 
-- 
-- Dependencies: 
-- 
-- Revision:
-- Revision 0.01 - File Created
-- Additional Comments:
-- 
----------------------------------------------------------------------------------


library IEEE;
use IEEE.STD_LOGIC_1164.ALL;
use IEEE.numeric_std.ALL;

use work.registers_pkg.all;

entity registers is

    Port ( 
        addr_a, addr_b, addr_w : in std_logic_vector(3 downto 0);
        w, rst, clk : in std_logic;
        data : in std_logic_vector(7 downto 0);
        a, b : out std_logic_vector(7 downto 0)
    );
end registers;

architecture Behavioral of registers is

    signal regs : register_array(0 to 15) := (
        3 => x"05",         -- Valeur arbitraire à l'index 3
        4 => x"06",         -- Valeur arbitraire à l'index 4
        others => (others => '0')
    );


begin

    process (clk)
    begin
        if rising_edge(clk) then
            if (rst = '0') then
                for i in 0 to 15 loop
                    regs(i) <= (others => '0');
                end loop;            
            elsif (w = '1') then
                regs(to_integer(unsigned(addr_w))) <= data;
            end if;
        end if;
        
    end process;

    a <= data when addr_w = addr_a else regs(to_integer(unsigned(addr_a)));
    b <= data when addr_w = addr_b else regs(to_integer(unsigned(addr_b)));

end Behavioral;

PROJET_INFO.srcs/sources_1/new/rom.vhd
----------------------------------------------------------------------------------
-- Company: 
-- Engineer: 
-- 
-- Create Date: 18.04.2025 17:50:07
-- Design Name: 
-- Module Name: rom - Behavioral
-- Project Name: 
-- Target Devices: 
-- Tool Versions: 
-- Description: 
-- 
-- Dependencies: 
-- 
-- Revision:
-- Revision 0.01 - File Created
-- Additional Comments:
-- 
----------------------------------------------------------------------------------

library IEEE;
use IEEE.STD_LOGIC_1164.ALL;
use IEEE.numeric_std.ALL;

use work.registers_pkg.all;

entity rom is

    Port ( 
        addr : in std_logic_vector(7 downto 0);
        clk : in std_logic;
        dout : out std_logic_vector(31 downto 0);
        dout_plus1 : out std_logic_vector(31 downto 0)
    );
end rom;

architecture Behavioral of rom is

    signal regs : rom_array(0 to 255) := (
        0 => x"06040100",
        1 => x"06050a00",
        2 => x"01020304",  -- valeur "au pif"
        others => (others => '0')
    );


begin

    process (clk)
    begin
        if rising_edge(clk) then
            dout <= regs(to_integer(unsigned(addr)));
            dout_plus1 <= regs(to_integer(unsigned(addr))+1);
        end if;
        
    end process;

end Behavioral;

PROJET_INFO.srcs/sources_1/new/counter_heightbits.vhd
library IEEE;
use IEEE.STD_LOGIC_1164.ALL;   
use IEEE.STD_LOGIC_ARITH.ALL;  
use IEEE.STD_LOGIC_UNSIGNED.ALL; 

entity counter_heightbits is
    port(
        clk : in std_logic;
        rst : in std_logic;
        load : in std_logic;
        sens : in std_logic;
        en : in std_logic;
        din : in std_logic_vector(7 downto 0);
        dout : out std_logic_vector(7 downto 0)
    );
end counter_heightbits;

architecture Behavioral of counter_heightbits is

    signal internal_counter : std_logic_vector(7 downto 0) := (others => '0');

begin

    process(clk)
    begin
        if rising_edge(clk) then
            if rst = '0' then
                internal_counter <= (others => '0');
            elsif load = '1' then
                internal_counter <= din;
            else
                if en = '0' then
                    if sens = '1' then
                        internal_counter <= internal_counter + 1;
                    else
                        internal_counter <= internal_counter - 1;
                    end if;                 
                end if;
            end if;         
        end if;
    end process;

    dout <= internal_counter;

end Behavioral;

PROJET_INFO.srcs/sources_1/new/clock_divider.vhd
----------------------------------------------------------------------------------
-- Company: 
-- Engineer: 
-- 
-- Create Date: 05.03.2025 17:10:06
-- Design Name: 
-- Module Name: clock_divider - Behavioral
-- Project Name: 
-- Target Devices: 
-- Tool Versions: 
-- Description: 
-- 
-- Dependencies: 
-- 
-- Revision:
-- Revision 0.01 - File Created
-- Additional Comments:
-- 
----------------------------------------------------------------------------------


library IEEE;
use IEEE.STD_LOGIC_1164.ALL;

entity clock_divider is
    generic(
        prescaler : integer := 50000000
    );

    Port(
        clk_in : in std_logic;
        clk_out : out std_logic
    );
end clock_divider;

architecture Behavioral of clock_divider is
    signal internal : integer range 0 to prescaler;
begin

    process (clk_in)
    begin
        if rising_edge(clk_in) then
            internal <= internal + 1;
            if (internal = prescaler) then
                internal <= 0;
            end if;
        end if;
    end process;

    clk_out <= '1' when internal = prescaler else '0';

end Behavioral;

PROJET_INFO.srcs/sources_1/new/micro.vhd
----------------------------------------------------------------------------------
-- Company: 
-- Engineer: 
-- 
-- Create Date: 18.04.2025 18:12:38
-- Design Name: 
-- Module Name: micro - Behavioral
-- Project Name: 
-- Target Devices: 
-- Tool Versions: 
-- Description: 
-- 
-- Dependencies: 
-- 
-- Revision:
-- Revision 0.01 - File Created
-- Additional Comments:
-- 
----------------------------------------------------------------------------------


library IEEE;
use IEEE.STD_LOGIC_1164.ALL;

entity micro is
    Port (
        clk_external   : in std_logic;
        rst            : in std_logic
    );
end micro;

architecture Behavioral of micro is

    signal clk_internal     : std_logic;
   
    signal pc_load          : std_logic;
    signal pc_way           : std_logic;
    signal pc_enable        : std_logic;
    signal pc_in            : std_logic_vector(7 downto 0);
    signal program_counter  : std_logic_vector(7 downto 0);
    
    -- NOP FLAG
    signal nop_flag         : std_logic;
    signal nop_flag_plus1   : std_logic;
    
    -- LI / DI IN
    signal rom_output       : std_logic_vector(31 downto 0);
    signal rom_a            : std_logic_vector(7 downto 0);
    signal rom_op           : std_logic_vector(7 downto 0);
    signal rom_b            : std_logic_vector(7 downto 0);
    signal rom_c            : std_logic_vector(7 downto 0);
    
    signal rom_output_plus1 : std_logic_vector(31 downto 0);
    signal rom_a_plus1            : std_logic_vector(7 downto 0);
    signal rom_op_plus1           : std_logic_vector(7 downto 0);
    signal rom_b_plus1           : std_logic_vector(7 downto 0);
    signal rom_c_plus1            : std_logic_vector(7 downto 0);
    
    -- DI OUT
    signal register_a       : std_logic_vector(7 downto 0);
    signal register_b       : std_logic_vector(7 downto 0);
    signal register_data    : std_logic_vector(7 downto 0);
    signal register_waddr   : std_logic_vector(3 downto 0);
    signal register_w       : std_logic;
    
    -- EX IN
    signal ex_in_a         : std_logic_vector(7 downto 0);
    signal ex_in_op        : std_logic_vector(7 downto 0);
    signal ex_in_b         : std_logic_vector(7 downto 0);
    signal ex_in_c         : std_logic_vector(7 downto 0);
    
    -- EX (OUT)
    signal ex_s            : std_logic_vector(7 downto 0);
    
    -- MEM IN
    signal mem_in_a         : std_logic_vector(7 downto 0);
    signal mem_in_op        : std_logic_vector(7 downto 0);
    signal mem_in_b         : std_logic_vector(7 downto 0);

    -- MEM INTERNAL
    signal mem_intern_addr  : std_logic_vector(7 downto 0);
    signal mem_intern_rw    : std_logic;
    
    -- MEM OUT
    signal mem_out_b        : std_logic_vector(7 downto 0);
    signal mem_mux_out      : std_logic_vector(7 downto 0);
    
    -- REGISTERS WRITING IN
    signal reg_w_a          : std_logic_vector(7 downto 0);
    signal reg_w_op         : std_logic_vector(7 downto 0);
    signal reg_w_b          : std_logic_vector(7 downto 0);
    
begin

    clk_div_inst: entity work.clock_divider -- clock divier
        generic map (
            prescaler => 2
        )
        port map (
            clk_in => clk_external,
            clk_out => clk_internal
        );
        
    pc_inst: entity work.counter_heightbits -- Program Counter
        port map (
            clk => clk_internal,
            rst => rst,
            load => pc_load,
            sens => pc_way,
            en => pc_enable,
            din => pc_in,
            dout => program_counter
        );
       
    pc_load <= '0';
    pc_way <= '1';
    
    rom_inst: entity work.rom -- ROM
        port map (
            addr => program_counter,
            clk => clk_internal,
            dout => rom_output,
            dout_plus1 => rom_output_plus1
        );

    registers_inst: entity work.registers -- Registers
        port map (
            addr_a => rom_b(3 downto 0),
            addr_b => rom_c(3 downto 0),
            addr_w => register_waddr,
            w => register_w,
            rst => rst,
            clk => clk_internal,
            data => register_data,
            a => register_a,
            b => register_b
        );
   
   
    di_proc : process(clk_internal) -- LI/DI
    begin
        if rising_edge(clk_internal) then
            if nop_flag = '1' then
                rom_op <= x"00";
                rom_a  <= (others => '0');
                rom_b  <= (others => '0');
                rom_c  <= (others => '0');
            else
                rom_op <= rom_output(31 downto 24);
                rom_a  <= rom_output(23 downto 16);
                rom_b  <= rom_output(15 downto 8);
                rom_c  <= rom_output(7 downto 0);
            end if;
        end if;
    end process;
    
    pc_enable <= nop_flag;
    
    process(rom_output, ex_in_op, ex_in_a, mem_in_op, mem_in_a, reg_w_op, reg_w_a)
        variable op  : std_logic_vector(7 downto 0);
        variable a   : std_logic_vector(7 downto 0);
        variable b   : std_logic_vector(7 downto 0);
        variable c   : std_logic_vector(7 downto 0);
    begin
        -- Parse the next instruction directly from ROM output
        op := rom_output(31 downto 24);
        a  := rom_output(23 downto 16);
        b  := rom_output(15 downto 8);
        c  := rom_output(7 downto 0);
    
        nop_flag <= '0';  -- Default
    
        -- DI hazard
        if op = x"06" and (a = b or a = c) then
            nop_flag <= '1';
        end if;
    
        -- EX hazard
        if ex_in_op = x"06" and (ex_in_a = b or ex_in_a = c) then
            nop_flag <= '1';
        end if;
    
        -- MEM hazard
        if mem_in_op = x"06" and (mem_in_a = b or mem_in_a = c) then
            nop_flag <= '1';
        end if;
    
        -- WB hazard
        if reg_w_op = x"06" and (reg_w_a = b or reg_w_a = c) then
            nop_flag <= '1';
        end if;
    end process;


    di_ex_proc : process (clk_internal) -- DI/EX
    begin
        if rising_edge(clk_internal) then
            -- DI MUX
            case rom_op is
                when x"01" =>  -- ADD
                    ex_in_b <= register_a;
                when x"06" =>  -- AFC
                    ex_in_b <= rom_b;
                when others =>
                    ex_in_b <= "00000000";
            end case;
            ex_in_a     <= rom_a;
            ex_in_op    <= rom_op;
            ex_in_c     <= register_b;
        end if;        
    end process;
    
    alu_inst : entity work.alu -- ALU
        port map (
            din_a => ex_in_b,
            din_b => ex_in_c,
            dout  => ex_s,
            op    => ex_in_op(3 downto 0)
        );
        
    ex_mem_proc : process (clk_internal) -- EX/MEM
    begin
        if rising_edge(clk_internal) then
            -- EX MUX
            case ex_in_op is
                when "00000001" =>  -- ADD
                    mem_in_b <= ex_s;
                when x"06" =>  -- AFC
                    mem_in_b <= ex_in_b;
                when others =>
                    mem_in_b <= "00000000";
            end case;
            mem_in_a    <= ex_in_a;
            mem_in_op   <= ex_in_op;
        end if;        
    end process;
    
    with mem_in_op select
        mem_intern_addr <= "00000000" when "00000001",  -- ADD
                           "00000000" when others;

    with mem_in_op select
        mem_intern_rw <= '1' when "00000001",  -- ADD
                           '1' when others;
                           
   ram_inst : entity work.ram -- RAM
   -- addr : in std_logic_vector(3 downto 0);
   -- rw, rst, clk : in std_logic;
   -- din : in std_logic_vector(7 downto 0);
   -- dout : out std_logic_vector(7 downto 0)
   port map (
        addr => mem_intern_addr,
        rw   => mem_intern_rw,
        rst  => rst,
        clk  => clk_internal,
        din  => mem_in_b,
        dout => mem_out_b
   );
   
   with mem_in_op select -- MEM OUT MUX (last one)
        mem_mux_out <=  mem_in_b when x"01",  -- ADD
                        mem_in_b when x"06",  -- AFC
                           "00000000" when others;
   
   mem_re_proc : process (clk_internal)
   begin
        if rising_edge(clk_internal) then
            reg_w_a     <= mem_in_a;
            reg_w_op    <= mem_in_op;
            reg_w_b     <= mem_mux_out;
        end if;
   end process;
   
   register_waddr   <= reg_w_a(3 downto 0);
   register_data    <= reg_w_b;

   with reg_w_op select
        register_w <=   '1' when x"01",  -- ADD
                        '1' when x"06",  -- AFC
                           '0' when others;

end Behavioral;

PROJET_INFO.srcs/sim_1/new/tb_micro.vhd
library IEEE;
use IEEE.STD_LOGIC_1164.ALL;
use IEEE.STD_LOGIC_UNSIGNED.ALL;

entity tb_micro is
end tb_micro;

architecture Behavioral of tb_micro is

    -- Signals to drive the design
    signal clk_external     : std_logic := '0';
    signal rst              : std_logic := '0';

    constant clk_period     : time := 10 ns;

begin

    -- Clock generation
    clk_process : process
    begin
        while true loop
            clk_external <= '0';
            wait for clk_period / 2;
            clk_external <= '1';
            wait for clk_period / 2;
        end loop;
    end process;

    -- Instantiate DUT
    uut: entity work.micro
        port map (
            clk_external => clk_external,
            rst => rst
        );

    -- Test process
    stim_proc: process
    begin
        -- Reset the design
        rst <= '1';
        --wait for 20 ns;
        --rst <= '0';

        wait for 500 ns;
        
        -- Stop the simulation
        wait;
    end process;

end Behavioral;

PROJET_INFO.sim/sim_1/behav/xsim/sim.vcd
$date
   Wed May  7 17:59:39 2025
$end

$version
  2024.2.0
$end

$timescale
  1ps
$end

$scope module tb_micro $end
$scope module uut $end
$var wire 1 ! clk_external $end
$var wire 1 " rst $end
$var wire 1 # clk_internal $end
$var wire 1 $ pc_load $end
$var wire 1 % pc_way $end
$var wire 1 & pc_enable $end
$var wire 8 ' pc_in $end
$var wire 8 ( program_counter $end
$var wire 1 ) nop_flag $end
$var wire 32 * rom_output $end
$var wire 8 + rom_a $end
$var wire 8 , rom_op $end
$var wire 8 - rom_b $end
$var wire 8 . rom_c $end
$var wire 32 / rom_output_plus1 $end
$var wire 8 0 rom_a_plus1 $end
$var wire 8 1 rom_op_plus1 $end
$var wire 8 2 rom_b_plus1 $end
$var wire 8 3 rom_c_plus1 $end
$var wire 8 4 register_a $end
$var wire 8 5 register_b $end
$var wire 8 6 register_data $end
$var wire 4 7 register_waddr $end
$var wire 1 8 register_w $end
$var wire 8 9 ex_in_a $end
$var wire 8 : ex_in_op $end
$var wire 8 ; ex_in_b $end
$var wire 8 < ex_in_c $end
$var wire 8 = ex_s $end
$var wire 8 > mem_in_a $end
$var wire 8 ? mem_in_op $end
$var wire 8 @ mem_in_b $end
$var wire 8 A mem_intern_addr $end
$var wire 1 B mem_intern_rw $end
$var wire 8 C mem_out_b $end
$var wire 8 D mem_mux_out $end
$var wire 8 E reg_w_a $end
$var wire 8 F reg_w_op $end
$var wire 8 G reg_w_b $end
$scope module clk_div_inst $end
$var wire 1 ! clk_in $end
$var wire 1 # clk_out $end
$upscope $end
$scope module pc_inst $end
$var wire 1 # clk $end
$var wire 1 " rst $end
$var wire 1 $ load $end
$var wire 1 % sens $end
$var wire 1 & en $end
$var wire 8 ' din $end
$var wire 8 ( dout $end
$var wire 8 H internal_counter $end
$upscope $end
$scope module rom_inst $end
$var wire 8 ( addr $end
$var wire 1 # clk $end
$var wire 32 * dout $end
$var wire 32 / dout_plus1 $end
$upscope $end
$scope module registers_inst $end
$var wire 4 I addr_a $end
$var wire 4 J addr_b $end
$var wire 4 7 addr_w $end
$var wire 1 8 w $end
$var wire 1 " rst $end
$var wire 1 # clk $end
$var wire 8 6 data $end
$var wire 8 4 a $end
$var wire 8 5 b $end
$scope task line__49 $end
$upscope $end
$upscope $end
$scope module alu_inst $end
$var wire 8 ; din_a $end
$var wire 8 < din_b $end
$var wire 8 = dout $end
$var wire 4 K op $end
$var wire 1 L fcarry $end
$var wire 1 M foverflow $end
$var wire 1 N fnegative $end
$var wire 1 O fzero $end
$var wire 8 P tmp $end
$upscope $end
$scope module ram_inst $end
$var wire 8 A addr $end
$var wire 1 B rw $end
$var wire 1 " rst $end
$var wire 1 # clk $end
$var wire 8 @ din $end
$var wire 8 C dout $end
$scope task line__44 $end
$upscope $end
$upscope $end
$upscope $end
$upscope $end
$enddefinitions $end

#1000000
$dumpvars
0!
1"
0#
0$
1%
0&
bx '
b11111 (
0)
b0 *
b0 +
b0 ,
b0 -
b0 .
b0 /
b0 0
b0 1
b0 2
b0 3
b0 4
b0 5
b0 6
b0 7
08
b0 9
b0 :
b0 ;
b0 <
b0 =
b0 >
b0 ?
b0 @
b0 A
1B
bx C
b0 D
b0 E
b0 F
b0 G
b11111 H
b0 I
b0 J
b0 K
0L
0M
0N
1O
b0 P
$end

#1005000
1!
1#
b100000 (
b100000 H

#1010000
0!

#1015000
1!
0#

#1020000
0!

#1025000
1!

#1030000
0!

#1035000
1!
1#
b100001 (
b100001 H

#1040000
0!

#1045000
1!
0#

#1050000
0!

#1055000
1!

#1060000
0!

#1065000
1!
1#
b100010 (
b100010 H

#1070000
0!

#1075000
1!
0#

#1080000
0!

#1085000
1!

#1090000
0!

#1095000
1!
1#
b100011 (
b100011 H

#1100000
0!

#1105000
1!
0#

#1110000
0!

#1115000
1!

#1120000
0!

#1125000
1!
1#
b100100 (
b100100 H

#1130000
0!

#1135000
1!
0#

#1140000
0!

#1145000
1!

#1150000
0!

#1155000
1!
1#
b100101 (
b100101 H

#1160000
0!

#1165000
1!
0#

#1170000
0!

#1175000
1!

#1180000
0!

#1185000
1!
1#
b100110 (
b100110 H

#1190000
0!

#1195000
1!
0#

#1200000
0!

#1205000
1!

#1210000
0!

#1215000
1!
1#
b100111 (
b100111 H

#1220000
0!

#1225000
1!
0#

#1230000
0!

#1235000
1!

#1240000
0!

#1245000
1!
1#
b101000 (
b101000 H

#1250000
0!

#1255000
1!
0#

#1260000
0!

#1265000
1!

#1270000
0!

#1275000
1!
1#
b101001 (
b101001 H

#1280000
0!

#1285000
1!
0#

#1290000
0!

#1295000
1!

#1300000
0!

#1305000
1!
1#
b101010 (
b101010 H

#1310000
0!

#1315000
1!
0#

#1320000
0!

#1325000
1!

#1330000
0!

#1335000
1!
1#
b101011 (
b101011 H

#1340000
0!

#1345000
1!
0#

#1350000
0!

#1355000
1!

#1360000
0!

#1365000
1!
1#
b101100 (
b101100 H

#1370000
0!

#1375000
1!
0#

#1380000
0!

#1385000
1!

#1390000
0!

#1395000
1!
1#
b101101 (
b101101 H

#1400000
0!

#1405000
1!
0#

#1410000
0!

#1415000
1!

#1420000
0!

#1425000
1!
1#
b101110 (
b101110 H

#1430000
0!

#1435000
1!
0#

#1440000
0!

#1445000
1!

#1450000
0!

#1455000
1!
1#
b101111 (
b101111 H

#1460000
0!

#1465000
1!
0#

#1470000
0!

#1475000
1!

#1480000
0!

#1485000
1!
1#
b110000 (
b110000 H

#1490000
0!

#1495000
1!
0#

#1500000
0!

#1505000
1!

#1510000
0!

#1515000
1!
1#
b110001 (
b110001 H

#1520000
0!

#1525000
1!
0#

#1530000
0!

#1535000
1!

#1540000
0!

#1545000
1!
1#
b110010 (
b110010 H

#1550000
0!

#1555000
1!
0#

#1560000
0!

#1565000
1!

#1570000
0!

#1575000
1!
1#
b110011 (
b110011 H

#1580000
0!

#1585000
1!
0#

#1590000
0!

#1595000
1!

#1600000
0!

#1605000
1!
1#
b110100 (
b110100 H

#1610000
0!

#1615000
1!
0#

#1620000
0!

#1625000
1!

#1630000
0!

#1635000
1!
1#
b110101 (
b110101 H

#1640000
0!

#1645000
1!
0#

#1650000
0!

#1655000
1!

#1660000
0!

#1665000
1!
1#
b110110 (
b110110 H

#1670000
0!

#1675000
1!
0#

#1680000
0!

#1685000
1!

#1690000
0!

#1695000
1!
1#
b110111 (
b110111 H

#1700000
0!

#1705000
1!
0#

#1710000
0!

#1715000
1!

#1720000
0!

#1725000
1!
1#
b111000 (
b111000 H

#1730000
0!

#1735000
1!
0#

#1740000
0!

#1745000
1!

#1750000
0!

#1755000
1!
1#
b111001 (
b111001 H

#1760000
0!

#1765000
1!
0#

#1770000
0!

#1775000
1!

#1780000
0!

#1785000
1!
1#
b111010 (
b111010 H

#1790000
0!

#1795000
1!
0#

#1800000
0!

#1805000
1!

#1810000
0!

#1815000
1!
1#
b111011 (
b111011 H

#1820000
0!

#1825000
1!
0#

#1830000
0!

#1835000
1!

#1840000
0!

#1845000
1!
1#
b111100 (
b111100 H

#1850000
0!

#1855000
1!
0#

#1860000
0!

#1865000
1!

#1870000
0!

#1875000
1!
1#
b111101 (
b111101 H

#1880000
0!

#1885000
1!
0#

#1890000
0!

#1895000
1!

#1900000
0!

#1905000
1!
1#
b111110 (
b111110 H

#1910000
0!

#1915000
1!
0#

#1920000
0!

#1925000
1!

#1930000
0!

#1935000
1!
1#
b111111 (
b111111 H

#1940000
0!

#1945000
1!
0#

#1950000
0!

#1955000
1!

#1960000
0!

#1965000
1!
1#
b1000000 (
b1000000 H

#1970000
0!

#1975000
1!
0#

#1980000
0!

#1985000
1!

#1990000
0!

#1995000
1!
1#
b1000001 (
b1000001 H

#2000000
0!

#2005000
1!
0#

#2010000
0!

#2015000
1!

#2020000
0!

#2025000
1!
1#
b1000010 (
b1000010 H

#2030000
0!

#2035000
1!
0#

#2040000
0!

#2045000
1!

#2050000
0!

#2055000
1!
1#
b1000011 (
b1000011 H

#2060000
0!

#2065000
1!
0#

#2070000
0!

#2075000
1!

#2080000
0!

#2085000
1!
1#
b1000100 (
b1000100 H

#2090000
0!

#2095000
1!
0#

#2100000
0!

#2105000
1!

#2110000
0!

#2115000
1!
1#
b1000101 (
b1000101 H

#2120000
0!

#2125000
1!
0#

#2130000
0!

#2135000
1!

#2140000
0!

#2145000
1!
1#
b1000110 (
b1000110 H

#2150000
0!

#2155000
1!
0#

#2160000
0!

#2165000
1!

#2170000
0!

#2175000
1!
1#
b1000111 (
b1000111 H

#2180000
0!

#2185000
1!
0#

#2190000
0!

#2195000
1!

#2200000
0!

#2205000
1!
1#
b1001000 (
b1001000 H

#2210000
0!

#2215000
1!
0#

#2220000
0!

#2225000
1!

#2230000
0!

#2235000
1!
1#
b1001001 (
b1001001 H

#2240000
0!

#2245000
1!
0#

#2250000
0!

#2255000
1!

#2260000
0!

#2265000
1!
1#
b1001010 (
b1001010 H

#2270000
0!

#2275000
1!
0#

#2280000
0!

#2285000
1!

#2290000
0!

#2295000
1!
1#
b1001011 (
b1001011 H

#2300000
0!

#2305000
1!
0#

#2310000
0!

#2315000
1!

#2320000
0!

#2325000
1!
1#
b1001100 (
b1001100 H

#2330000
0!

#2335000
1!
0#

#2340000
0!

#2345000
1!

#2350000
0!

#2355000
1!
1#
b1001101 (
b1001101 H

#2360000
0!

#2365000
1!
0#

#2370000
0!

#2375000
1!

#2380000
0!

#2385000
1!
1#
b1001110 (
b1001110 H

#2390000
0!

#2395000
1!
0#

#2400000
0!

#2405000
1!

#2410000
0!

#2415000
1!
1#
b1001111 (
b1001111 H

#2420000
0!

#2425000
1!
0#

#2430000
0!

#2435000
1!

#2440000
0!

#2445000
1!
1#
b1010000 (
b1010000 H

#2450000
0!

#2455000
1!
0#

#2460000
0!

#2465000
1!

#2470000
0!

#2475000
1!
1#
b1010001 (
b1010001 H

#2480000
0!

#2485000
1!
0#

#2490000
0!

#2495000
1!

#2500000
0!

#2505000
1!
1#
b1010010 (
b1010010 H

#2510000
0!

#2515000
1!
0#

#2520000
0!

#2525000
1!

#2530000
0!

#2535000
1!
1#
b1010011 (
b1010011 H

#2540000
0!

#2545000
1!
0#

#2550000
0!

#2555000
1!

#2560000
0!

#2565000
1!
1#
b1010100 (
b1010100 H

#2570000
0!

#2575000
1!
0#

#2580000
0!

#2585000
1!

#2590000
0!

#2595000
1!
1#
b1010101 (
b1010101 H

#2600000
0!

#2605000
1!
0#

#2610000
0!

#2615000
1!

#2620000
0!

#2625000
1!
1#
b1010110 (
b1010110 H

#2630000
0!

#2635000
1!
0#

#2640000
0!

#2645000
1!

#2650000
0!

#2655000
1!
1#
b1010111 (
b1010111 H

#2660000
0!

#2665000
1!
0#

#2670000
0!

#2675000
1!

#2680000
0!

#2685000
1!
1#
b1011000 (
b1011000 H

#2690000
0!

#2695000
1!
0#

#2700000
0!

#2705000
1!

#2710000
0!

#2715000
1!
1#
b1011001 (
b1011001 H

#2720000
0!

#2725000
1!
0#

#2730000
0!

#2735000
1!

#2740000
0!

#2745000
1!
1#
b1011010 (
b1011010 H

#2750000
0!

#2755000
1!
0#

#2760000
0!

#2765000
1!

#2770000
0!

#2775000
1!
1#
b1011011 (
b1011011 H

#2780000
0!

#2785000
1!
0#

#2790000
0!

#2795000
1!

#2800000
0!

#2805000
1!
1#
b1011100 (
b1011100 H

#2810000
0!

#2815000
1!
0#

#2820000
0!

#2825000
1!

#2830000
0!

#2835000
1!
1#
b1011101 (
b1011101 H

#2840000
0!

#2845000
1!
0#

#2850000
0!

#2855000
1!

#2860000
0!

#2865000
1!
1#
b1011110 (
b1011110 H

#2870000
0!

#2875000
1!
0#

#2880000
0!

#2885000
1!

#2890000
0!

#2895000
1!
1#
b1011111 (
b1011111 H

#2900000
0!

#2905000
1!
0#

#2910000
0!

#2915000
1!

#2920000
0!

#2925000
1!
1#
b1100000 (
b1100000 H

#2930000
0!

#2935000
1!
0#

#2940000
0!

#2945000
1!

#2950000
0!

#2955000
1!
1#
b1100001 (
b1100001 H

#2960000
0!

#2965000
1!
0#

#2970000
0!

#2975000
1!

#2980000
0!

#2985000
1!
1#
b1100010 (
b1100010 H

#2990000
0!

#2995000
1!
0#

#3000000
0!

#3005000
1!

#3010000
0!

#3015000
1!
1#
b1100011 (
b1100011 H

#3020000
0!

#3025000
1!
0#

#3030000
0!

#3035000
1!

#3040000
0!

#3045000
1!
1#
b1100100 (
b1100100 H

#3050000
0!

#3055000
1!
0#

#3060000
0!

#3065000
1!

#3070000
0!

#3075000
1!
1#
b1100101 (
b1100101 H

#3080000
0!

#3085000
1!
0#

#3090000
0!

#3095000
1!

#3100000
0!

#3105000
1!
1#
b1100110 (
b1100110 H

#3110000
0!

#3115000
1!
0#

#3120000
0!

#3125000
1!

#3130000
0!

#3135000
1!
1#
b1100111 (
b1100111 H

#3140000
0!

#3145000
1!
0#

#3150000
0!

#3155000
1!

#3160000
0!

#3165000
1!
1#
b1101000 (
b1101000 H

#3170000
0!

#3175000
1!
0#

#3180000
0!

#3185000
1!

#3190000
0!

#3195000
1!
1#
b1101001 (
b1101001 H

#3200000
0!

#3205000
1!
0#

#3210000
0!

#3215000
1!

#3220000
0!

#3225000
1!
1#
b1101010 (
b1101010 H

#3230000
0!

#3235000
1!
0#

#3240000
0!

#3245000
1!

#3250000
0!

#3255000
1!
1#
b1101011 (
b1101011 H

#3260000
0!

#3265000
1!
0#

#3270000
0!

#3275000
1!

#3280000
0!

#3285000
1!
1#
b1101100 (
b1101100 H

#3290000
0!

#3295000
1!
0#

#3300000
0!

#3305000
1!

#3310000
0!

#3315000
1!
1#
b1101101 (
b1101101 H

#3320000
0!

#3325000
1!
0#

#3330000
0!

#3335000
1!

#3340000
0!

#3345000
1!
1#
b1101110 (
b1101110 H

#3350000
0!

#3355000
1!
0#

#3360000
0!

#3365000
1!

#3370000
0!

#3375000
1!
1#
b1101111 (
b1101111 H

#3380000
0!

#3385000
1!
0#

#3390000
0!

#3395000
1!

#3400000
0!

#3405000
1!
1#
b1110000 (
b1110000 H

#3410000
0!

#3415000
1!
0#

#3420000
0!

#3425000
1!

#3430000
0!

#3435000
1!
1#
b1110001 (
b1110001 H

#3440000
0!

#3445000
1!
0#

#3450000
0!

#3455000
1!

#3460000
0!

#3465000
1!
1#
b1110010 (
b1110010 H

#3470000
0!

#3475000
1!
0#

#3480000
0!

#3485000
1!

#3490000
0!

#3495000
1!
1#
b1110011 (
b1110011 H

#3500000
0!

#3505000
1!
0#

#3510000
0!

#3515000
1!

